{"curContainerId":"49454a05-3ca9-7c85-a032-715a6bf7b5e6","version":"1.9.1","containers":[{"__class":"Container","__uniqueId":"49454a05-3ca9-7c85-a032-715a6bf7b5e6","graph":{"__class":"ScriptGraph","__uniqueId":"8cbbbf7b-0cd9-bce3-4889-e9ce71dc479f","panelName":"Visual Scripting","graphType":"SCRIPT","editable":true,"transform":{"a":0.9090914755738732,"c":0,"e":-44226.971076961374,"b":0,"d":0.9090914755738732,"f":-44765.84748949307},"transformLocal":{"a":0.9090914755738732,"c":0,"e":-44515.971076961374,"b":0,"d":0.9090914755738732,"f":-45183.84748949307},"scaleTransformLocal":{"a":1,"b":0,"c":0,"d":1,"e":0,"f":0},"nodeList":[{"__class":"PropertyNode","__uniqueId":"19d15f19-b3c0-0605-2054-5533cf9c4dec","nodeType":"SCRIPT","position":{"x":49859.2949796988,"y":49693.03325190168},"name":"Turret","owner":{"__referenceId":"8cbbbf7b-0cd9-bce3-4889-e9ce71dc479f"},"size":{"width":164,"height":132},"description":"","category":"Pin","deletable":true,"cloneable":true,"inputPorts":[{"__class":"ScriptPort","__uniqueId":"d11bc465-d417-eef4-ae25-a31812163315","portName":"Set","type":"CONTROL","isInput":true,"isConnected":true,"isDynamic":false,"centerPosition":{"x":49873.294979698796,"y":49781.03325190168},"valueTypeName":"Pulse","portIndex":0,"portValue":{"type":"Pulse","value":false},"visible":true,"refEdges":[{"__class":"Edge","__uniqueId":"65328099-c59d-39f7-bbd6-f1b68d9ddb28","owner":{"__referenceId":"8cbbbf7b-0cd9-bce3-4889-e9ce71dc479f"},"type":"BEZIER","sourcePortPosition":{"x":49753.73122763622,"y":49710.47619298569},"targetPortPosition":{"x":49873.294979698796,"y":49781.03325190168},"sourcePort":{"__class":"ScriptPort","__uniqueId":"c24ec1cd-13c4-5567-46c9-8bb45c1241e3","portName":"Next","type":"CONTROL","isInput":false,"isConnected":true,"isDynamic":false,"centerPosition":{"x":49753.73122763622,"y":49710.47619298569},"valueTypeName":"Pulse","portIndex":0,"portValue":null,"visible":true,"refEdges":[{"__referenceId":"65328099-c59d-39f7-bbd6-f1b68d9ddb28"}],"owner":{"__class":"ScriptTemplateNode","__uniqueId":"fc9032c3-0aaf-6c48-c4e2-6e1c118d77d0","nodeType":"SCRIPT","position":{"x":49603.73122763622,"y":49662.47619298569},"name":"Update","owner":{"__referenceId":"8cbbbf7b-0cd9-bce3-4889-e9ce71dc479f"},"size":{"width":164,"height":92},"description":"Execute the next node in every frame.","category":"Event","deletable":true,"cloneable":true,"inputPorts":[],"outputPorts":[{"__referenceId":"c24ec1cd-13c4-5567-46c9-8bb45c1241e3"},{"__class":"ScriptPort","__uniqueId":"39a26bb7-6d4c-f73c-7da7-9133bd02b1e2","portName":"Delta Time","type":"DATA","isInput":false,"isConnected":false,"isDynamic":false,"centerPosition":{"x":49753.73122763622,"y":49734.47619298569},"valueTypeName":"Double","portIndex":1,"portValue":null,"visible":true,"refEdges":[],"owner":{"__referenceId":"fc9032c3-0aaf-6c48-c4e2-6e1c118d77d0"},"hideInput":false,"valueList":[],"addManually":false}],"error":false,"groupEnable":true,"renamable":false,"nodeSettings":[{"key":"Description","property":[{"type":"String","section":"Description","key":"Node Desc","value":"Execute the next node in every frame.","editable":false}]}],"nodeName":"","templateGuid":"76dd06cb-6f7a-60eb-e2fa-c9b10a0c78fc","curSelectedType":"","containResource":false,"version":"1.0.1","compatibleState":0,"addableInputConfig":null,"addableOutputConfig":null,"portAddable":0},"hideInput":false,"valueList":[],"addManually":false},"targetPort":{"__referenceId":"d11bc465-d417-eef4-ae25-a31812163315"},"isValid":true}],"owner":{"__referenceId":"19d15f19-b3c0-0605-2054-5533cf9c4dec"},"hideInput":false,"valueList":[],"addManually":false},{"__class":"ScriptPort","__uniqueId":"07be7a98-9c5b-d44a-74b0-f2b5be5bda56","portName":"Value","type":"DATA","isInput":true,"isConnected":true,"isDynamic":false,"centerPosition":{"x":49873.294979698796,"y":49805.03325190169},"valueTypeName":"Double","portIndex":1,"portValue":{"type":"Number","value":57.93961496997898},"visible":true,"refEdges":[{"__class":"Edge","__uniqueId":"62b14b67-033c-28ec-28a5-f17c6aedafdd","owner":{"__referenceId":"8cbbbf7b-0cd9-bce3-4889-e9ce71dc479f"},"type":"BEZIER","sourcePortPosition":{"x":49751.50022274535,"y":49903.21844408025},"targetPortPosition":{"x":49873.294979698796,"y":49805.03325190169},"sourcePort":{"__class":"ScriptPort","__uniqueId":"b83ec703-bb8d-a1cf-d5dc-bad6b705b696","portName":"Current","type":"DATA","isInput":false,"isConnected":true,"isDynamic":true,"centerPosition":{"x":49751.50022274535,"y":49903.21844408025},"valueTypeName":"Double","portIndex":3,"portValue":null,"visible":true,"refEdges":[{"__referenceId":"62b14b67-033c-28ec-28a5-f17c6aedafdd"}],"owner":{"__class":"ScriptTemplateNode","__uniqueId":"c9d90f3a-e6ee-c64c-d970-002b7c909c0a","nodeType":"SCRIPT","position":{"x":49483.50022274535,"y":49783.21844408025},"name":"Transit by Time","owner":{"__referenceId":"8cbbbf7b-0cd9-bce3-4889-e9ce71dc479f"},"size":{"width":282,"height":380},"description":"Transition from one value to another according to a certain interpolator within a certain time range. Supported types: Number, Vec2, Vec3, Vec4, and Color.","category":"Utility","deletable":true,"cloneable":true,"inputPorts":[{"__class":"ScriptPort","__uniqueId":"b5a61365-7450-6c3e-a2e3-d6a3a07dc6a1","portName":"Start","type":"CONTROL","isInput":true,"isConnected":true,"isDynamic":false,"centerPosition":{"x":49497.50022274535,"y":49927.21844408026},"valueTypeName":"Pulse","portIndex":0,"portValue":{"type":"Pulse","value":false},"visible":true,"refEdges":[{"__class":"Edge","__uniqueId":"4e1f74a3-b7b1-113f-82c7-3b4f87995567","owner":{"__referenceId":"8cbbbf7b-0cd9-bce3-4889-e9ce71dc479f"},"type":"BEZIER","sourcePortPosition":{"x":49420.25104889151,"y":49926.85142030939},"targetPortPosition":{"x":49497.50022274535,"y":49927.21844408026},"sourcePort":{"__class":"ScriptPort","__uniqueId":"a9d4025c-0f09-a844-c1b3-30b2ea794f51","portName":"Next","type":"CONTROL","isInput":false,"isConnected":true,"isDynamic":false,"centerPosition":{"x":49420.25104889151,"y":49926.85142030939},"valueTypeName":"Pulse","portIndex":0,"portValue":null,"visible":true,"refEdges":[{"__referenceId":"4e1f74a3-b7b1-113f-82c7-3b4f87995567"}],"owner":{"__class":"ScriptTemplateNode","__uniqueId":"eeb05261-de97-b418-0e05-3ab7c4bf8d34","nodeType":"SCRIPT","position":{"x":49270.25104889151,"y":49878.85142030939},"name":"Start","owner":{"__referenceId":"8cbbbf7b-0cd9-bce3-4889-e9ce71dc479f"},"size":{"width":164,"height":68},"description":"Execute the next node when an effect starts.","category":"Event","deletable":true,"cloneable":true,"inputPorts":[],"outputPorts":[{"__referenceId":"a9d4025c-0f09-a844-c1b3-30b2ea794f51"}],"error":false,"groupEnable":true,"renamable":false,"nodeSettings":[{"key":"Description","property":[{"type":"String","section":"Description","key":"Node Desc","value":"Execute the next node when an effect starts.","editable":false}]}],"nodeName":"","templateGuid":"2f0fed0f-5279-9602-3083-5e1fb8163563","curSelectedType":"","containResource":false,"version":"1.0.1","compatibleState":0,"addableInputConfig":null,"addableOutputConfig":null,"portAddable":0},"hideInput":false,"valueList":[],"addManually":false},"targetPort":{"__referenceId":"b5a61365-7450-6c3e-a2e3-d6a3a07dc6a1"},"isValid":true}],"owner":{"__referenceId":"c9d90f3a-e6ee-c64c-d970-002b7c909c0a"},"hideInput":false,"valueList":[],"addManually":false},{"__class":"ScriptPort","__uniqueId":"58b3dcdf-4cfe-9963-5331-7d2ab6c46576","portName":"Pause","type":"CONTROL","isInput":true,"isConnected":false,"isDynamic":false,"centerPosition":{"x":49497.50022274535,"y":49951.21844408025},"valueTypeName":"Pulse","portIndex":1,"portValue":{"type":"Pulse","value":false},"visible":true,"refEdges":[],"owner":{"__referenceId":"c9d90f3a-e6ee-c64c-d970-002b7c909c0a"},"hideInput":false,"valueList":[],"addManually":false},{"__class":"ScriptPort","__uniqueId":"84f0fbeb-b606-3e91-1725-ba5eb97d98b9","portName":"Resume","type":"CONTROL","isInput":true,"isConnected":false,"isDynamic":false,"centerPosition":{"x":49497.50022274535,"y":49975.21844408026},"valueTypeName":"Pulse","portIndex":2,"portValue":{"type":"Pulse","value":false},"visible":true,"refEdges":[],"owner":{"__referenceId":"c9d90f3a-e6ee-c64c-d970-002b7c909c0a"},"hideInput":false,"valueList":[],"addManually":false},{"__class":"ScriptPort","__uniqueId":"020f26a6-5736-13f6-14c7-e7e729558ca0","portName":"Stop","type":"CONTROL","isInput":true,"isConnected":false,"isDynamic":false,"centerPosition":{"x":49497.50022274535,"y":49999.21844408025},"valueTypeName":"Pulse","portIndex":3,"portValue":{"type":"Pulse","value":false},"visible":true,"refEdges":[],"owner":{"__referenceId":"c9d90f3a-e6ee-c64c-d970-002b7c909c0a"},"hideInput":false,"valueList":[],"addManually":false},{"__class":"ScriptPort","__uniqueId":"ffeced9d-ee7e-7027-2963-dcf5f81a277f","portName":"From","type":"DATA","isInput":true,"isConnected":true,"isDynamic":true,"centerPosition":{"x":49497.50022274535,"y":50023.21844408026},"valueTypeName":"Double","portIndex":4,"portValue":{"type":"Number","value":50},"visible":true,"refEdges":[{"__class":"Edge","__uniqueId":"a8d992db-eb42-f225-892e-d7facd301311","owner":{"__referenceId":"8cbbbf7b-0cd9-bce3-4889-e9ce71dc479f"},"type":"BEZIER","sourcePortPosition":{"x":49418.02257881362,"y":50024.02580943552},"targetPortPosition":{"x":49497.50022274535,"y":50023.21844408026},"sourcePort":{"__class":"GroupPort","__uniqueId":"d6b758d0-3d98-1871-d9a2-29e5a081de89","portName":"From Angle","type":"DATA","isInput":false,"isConnected":true,"isDynamic":true,"centerPosition":{"x":49418.02257881362,"y":50024.02580943552},"valueTypeName":"Double","portIndex":0,"portValue":null,"visible":true,"refEdges":[{"__referenceId":"a8d992db-eb42-f225-892e-d7facd301311"}],"owner":{"__class":"Group","__uniqueId":"69e987a9-727e-53f8-1aa4-8bf60e18b81a","nodeType":"GROUP","position":{"x":49123.02257881362,"y":49974.025809435516},"name":"Set Cannon Angles","owner":{"__referenceId":"8cbbbf7b-0cd9-bce3-4889-e9ce71dc479f"},"size":{"width":309,"height":96},"description":"","category":"Group","deletable":true,"cloneable":true,"inputPorts":[{"__class":"GroupPort","__uniqueId":"c396e96c-31b9-5f3a-bbfe-e277de950b40","portName":"Central Angle","type":"DATA","isInput":true,"isConnected":false,"isDynamic":false,"centerPosition":{"x":49137.02257881362,"y":50024.02580943552},"valueTypeName":"Double","portIndex":0,"portValue":{"type":"Number","value":90},"visible":true,"refEdges":[],"owner":{"__referenceId":"69e987a9-727e-53f8-1aa4-8bf60e18b81a"},"hideInput":false,"relatedPlaceholderPort":{"__class":"PlaceholderPort","__uniqueId":"ee111d3c-beed-ccee-798c-4b422b7e4006","portName":"Central Angle","type":"DATA","isInput":false,"isConnected":true,"isDynamic":true,"centerPosition":{"x":48933.04139330203,"y":50052.196802974395},"valueTypeName":"Double","portIndex":0,"portValue":null,"visible":true,"refEdges":[{"__class":"Edge","__uniqueId":"9c7e5917-a2ad-e495-d174-ce9589d67d31","owner":{"__class":"ScriptGraph","__uniqueId":"8dff5d39-c77e-b4dd-12fd-95919262d695","panelName":"Visual Scripting","graphType":"SCRIPT","editable":true,"transform":{"a":0.6075834724021041,"c":0,"e":-29213.134087255024,"b":0,"d":0.6075834724021041,"f":-29708.707205475137},"transformLocal":{"a":0.6075834724021041,"c":0,"e":-29502.134087255024,"b":0,"d":0.6075834724021041,"f":-30126.707205475137},"scaleTransformLocal":{"a":1,"b":0,"c":0,"d":1,"e":0,"f":0},"nodeList":[{"__class":"Placeholder","__uniqueId":"3fe0f73a-5903-9d02-193c-6376e6a133db","nodeType":"PLACEHOLDER","position":{"x":48686.04139330203,"y":50006.19680297439},"name":"Input","owner":{"__referenceId":"8dff5d39-c77e-b4dd-12fd-95919262d695"},"size":{"width":259,"height":160},"description":"","category":"Input_Placeholder","deletable":false,"cloneable":false,"inputPorts":[],"outputPorts":[{"__referenceId":"ee111d3c-beed-ccee-798c-4b422b7e4006"},{"__class":"PlaceholderPort","__uniqueId":"2e8033b0-a7af-068d-48e9-af90fbee711f","portName":"Total Angle Range","type":"DATA","isInput":false,"isConnected":true,"isDynamic":true,"centerPosition":{"x":48933.04139330203,"y":50076.196802974395},"valueTypeName":"Double","portIndex":1,"portValue":null,"visible":true,"refEdges":[{"__class":"Edge","__uniqueId":"71033a66-1fcc-ba29-24f1-afb4e62c780d","owner":{"__referenceId":"8dff5d39-c77e-b4dd-12fd-95919262d695"},"type":"BEZIER","sourcePortPosition":{"x":48933.04139330203,"y":50076.196802974395},"targetPortPosition":{"x":49023.59905726818,"y":50079.177250550696},"sourcePort":{"__referenceId":"2e8033b0-a7af-068d-48e9-af90fbee711f"},"targetPort":{"__class":"ScriptPort","__uniqueId":"fda8945e-4e9d-1132-3494-263f71992359","portName":"A","type":"DATA","isInput":true,"isConnected":true,"isDynamic":true,"centerPosition":{"x":49023.59905726818,"y":50079.177250550696},"valueTypeName":"Double","portIndex":0,"portValue":{"type":"Number","value":80},"visible":true,"refEdges":[{"__referenceId":"71033a66-1fcc-ba29-24f1-afb4e62c780d"}],"owner":{"__class":"ScriptTemplateNode","__uniqueId":"74991fa6-e0c4-37be-6160-8c2c5a703392","nodeType":"SCRIPT","position":{"x":49009.59905726818,"y":50007.177250550696},"name":"Multiply","owner":{"__referenceId":"8dff5d39-c77e-b4dd-12fd-95919262d695"},"size":{"width":170,"height":136},"description":"Multiply two values. You can click \"+\" to add more inputs. Supported types: Number, Vec2, Vec3, and Vec4.","category":"Math","deletable":true,"cloneable":true,"inputPorts":[{"__referenceId":"fda8945e-4e9d-1132-3494-263f71992359"},{"__class":"ScriptPort","__uniqueId":"15dfe68d-2530-0983-447b-7fa533a9080e","portName":"B","type":"DATA","isInput":true,"isConnected":false,"isDynamic":true,"centerPosition":{"x":49023.59905726818,"y":50103.1772505507},"valueTypeName":"Double","portIndex":1,"portValue":{"type":"Number","value":0.5},"visible":true,"refEdges":[],"owner":{"__referenceId":"74991fa6-e0c4-37be-6160-8c2c5a703392"},"hideInput":false,"valueList":[],"addManually":false}],"outputPorts":[{"__class":"ScriptPort","__uniqueId":"685dcc4a-6cc3-79d7-c92f-26b6de0e2577","portName":"A*B","type":"DATA","isInput":false,"isConnected":true,"isDynamic":true,"centerPosition":{"x":49165.59905726818,"y":50055.177250550696},"valueTypeName":"Double","portIndex":0,"portValue":null,"visible":true,"refEdges":[{"__class":"Edge","__uniqueId":"bdeb997b-2bde-6e60-a479-ddb0c239df64","owner":{"__referenceId":"8dff5d39-c77e-b4dd-12fd-95919262d695"},"type":"BEZIER","sourcePortPosition":{"x":49165.59905726818,"y":50055.177250550696},"targetPortPosition":{"x":49257.70577748387,"y":50176.52924447629},"sourcePort":{"__referenceId":"685dcc4a-6cc3-79d7-c92f-26b6de0e2577"},"targetPort":{"__class":"ScriptPort","__uniqueId":"eb0c2349-10a0-56a8-fa51-8dd88e72bd1e","portName":"B","type":"DATA","isInput":true,"isConnected":true,"isDynamic":true,"centerPosition":{"x":49257.70577748387,"y":50176.52924447629},"valueTypeName":"Double","portIndex":1,"portValue":{"type":"Number","value":40},"visible":true,"refEdges":[{"__referenceId":"bdeb997b-2bde-6e60-a479-ddb0c239df64"}],"owner":{"__class":"ScriptTemplateNode","__uniqueId":"4a05810c-b71b-a28d-e05d-01d173e5a778","nodeType":"SCRIPT","position":{"x":49243.70577748387,"y":50080.52924447629},"name":"Add","owner":{"__referenceId":"8dff5d39-c77e-b4dd-12fd-95919262d695"},"size":{"width":164,"height":136},"description":"Calculate the sum of two inputs. You can click \"+\" to add more inputs. Supported types: Number, Vec2, Vec3, and Vec4.","category":"Math","deletable":true,"cloneable":true,"inputPorts":[{"__class":"ScriptPort","__uniqueId":"b175bed4-7e00-804e-f582-24f37cbf87c3","portName":"A","type":"DATA","isInput":true,"isConnected":true,"isDynamic":true,"centerPosition":{"x":49257.70577748387,"y":50152.529244476296},"valueTypeName":"Double","portIndex":0,"portValue":{"type":"Number","value":90},"visible":true,"refEdges":[{"__class":"Edge","__uniqueId":"fc89eebc-243f-1f3e-46d9-31c51bf14251","owner":{"__referenceId":"8dff5d39-c77e-b4dd-12fd-95919262d695"},"type":"BEZIER","sourcePortPosition":{"x":48933.04139330203,"y":50052.196802974395},"targetPortPosition":{"x":49257.70577748387,"y":50152.529244476296},"sourcePort":{"__referenceId":"ee111d3c-beed-ccee-798c-4b422b7e4006"},"targetPort":{"__referenceId":"b175bed4-7e00-804e-f582-24f37cbf87c3"},"isValid":true}],"owner":{"__referenceId":"4a05810c-b71b-a28d-e05d-01d173e5a778"},"hideInput":false,"valueList":[],"addManually":false},{"__referenceId":"eb0c2349-10a0-56a8-fa51-8dd88e72bd1e"}],"outputPorts":[{"__class":"ScriptPort","__uniqueId":"994ad496-90db-91ec-2719-78c78ba5f43d","portName":"A+B","type":"DATA","isInput":false,"isConnected":true,"isDynamic":true,"centerPosition":{"x":49393.70577748387,"y":50128.529244476296},"valueTypeName":"Double","portIndex":0,"portValue":null,"visible":true,"refEdges":[{"__class":"Edge","__uniqueId":"603c4e97-badd-bbe0-d372-44038b0572f2","owner":{"__referenceId":"8dff5d39-c77e-b4dd-12fd-95919262d695"},"type":"BEZIER","sourcePortPosition":{"x":49393.70577748387,"y":50128.529244476296},"targetPortPosition":{"x":49528.27761202413,"y":50069.51342866172},"sourcePort":{"__referenceId":"994ad496-90db-91ec-2719-78c78ba5f43d"},"targetPort":{"__class":"PlaceholderPort","__uniqueId":"8a645b24-a8b9-5bf9-8161-c987bdac753c","portName":"To Angle","type":"DATA","isInput":true,"isConnected":true,"isDynamic":true,"centerPosition":{"x":49528.27761202413,"y":50069.51342866172},"valueTypeName":"Double","portIndex":1,"portValue":{"type":"Number","value":130},"visible":true,"refEdges":[{"__referenceId":"603c4e97-badd-bbe0-d372-44038b0572f2"}],"owner":{"__class":"Placeholder","__uniqueId":"15cef1bf-1690-7225-35e2-3a56d74c5924","nodeType":"PLACEHOLDER","position":{"x":49510.27761202413,"y":49999.51342866171},"name":"Output","owner":{"__referenceId":"8dff5d39-c77e-b4dd-12fd-95919262d695"},"size":{"width":212,"height":160},"description":"","category":"Output_Placeholder","deletable":false,"cloneable":false,"inputPorts":[{"__class":"PlaceholderPort","__uniqueId":"0317be88-f3ba-68be-a5ae-81ad6ee88d73","portName":"From Angle","type":"DATA","isInput":true,"isConnected":true,"isDynamic":true,"centerPosition":{"x":49528.27761202413,"y":50045.51342866171},"valueTypeName":"Double","portIndex":0,"portValue":{"type":"Number","value":50},"visible":true,"refEdges":[{"__class":"Edge","__uniqueId":"e0c1e67a-c97b-3ff6-9d36-dec5c45004ca","owner":{"__referenceId":"8dff5d39-c77e-b4dd-12fd-95919262d695"},"type":"BEZIER","sourcePortPosition":{"x":49403.86856818156,"y":49999.45947703444},"targetPortPosition":{"x":49528.27761202413,"y":50045.51342866171},"sourcePort":{"__class":"ScriptPort","__uniqueId":"d84c4be9-8c97-b549-4a4c-b4721887ae8d","portName":"A-B","type":"DATA","isInput":false,"isConnected":true,"isDynamic":true,"centerPosition":{"x":49403.86856818156,"y":49999.45947703444},"valueTypeName":"Double","portIndex":0,"portValue":null,"visible":true,"refEdges":[{"__referenceId":"e0c1e67a-c97b-3ff6-9d36-dec5c45004ca"}],"owner":{"__class":"ScriptTemplateNode","__uniqueId":"9a07b317-3676-84b9-3b9b-a6d4aa52aaba","nodeType":"SCRIPT","position":{"x":49244.86856818156,"y":49951.459477034434},"name":"Subtract","owner":{"__referenceId":"8dff5d39-c77e-b4dd-12fd-95919262d695"},"size":{"width":173,"height":116},"description":"Subtract one value by another. Supported types: Number, Vec2, Vec3, and Vec4.","category":"Math","deletable":true,"cloneable":true,"inputPorts":[{"__class":"ScriptPort","__uniqueId":"83296790-7466-c18d-b608-5b08a4ab3dc0","portName":"A","type":"DATA","isInput":true,"isConnected":true,"isDynamic":true,"centerPosition":{"x":49258.86856818156,"y":50023.459477034434},"valueTypeName":"Double","portIndex":0,"portValue":{"type":"Number","value":90},"visible":true,"refEdges":[{"__referenceId":"9c7e5917-a2ad-e495-d174-ce9589d67d31"}],"owner":{"__referenceId":"9a07b317-3676-84b9-3b9b-a6d4aa52aaba"},"hideInput":false,"valueList":[],"addManually":false},{"__class":"ScriptPort","__uniqueId":"82cee720-eb8d-14f7-42d4-1b5bc9e409e6","portName":"B","type":"DATA","isInput":true,"isConnected":true,"isDynamic":true,"centerPosition":{"x":49258.86856818156,"y":50047.459477034434},"valueTypeName":"Double","portIndex":1,"portValue":{"type":"Number","value":40},"visible":true,"refEdges":[{"__class":"Edge","__uniqueId":"4938444a-d19b-0d77-eb1e-6e35c0548703","owner":{"__referenceId":"8dff5d39-c77e-b4dd-12fd-95919262d695"},"type":"BEZIER","sourcePortPosition":{"x":49165.59905726818,"y":50055.177250550696},"targetPortPosition":{"x":49258.86856818156,"y":50047.459477034434},"sourcePort":{"__referenceId":"685dcc4a-6cc3-79d7-c92f-26b6de0e2577"},"targetPort":{"__referenceId":"82cee720-eb8d-14f7-42d4-1b5bc9e409e6"},"isValid":true}],"owner":{"__referenceId":"9a07b317-3676-84b9-3b9b-a6d4aa52aaba"},"hideInput":false,"valueList":[],"addManually":false}],"outputPorts":[{"__referenceId":"d84c4be9-8c97-b549-4a4c-b4721887ae8d"}],"error":false,"groupEnable":true,"renamable":false,"nodeSettings":[{"key":"Description","property":[{"type":"String","section":"Description","key":"Node Desc","value":"Subtract one value by another. Supported types: Number, Vec2, Vec3, and Vec4.","editable":false}]}],"nodeName":"","templateGuid":"0ac9aa66-03f2-395a-fb0c-690c22a2d6b6","curSelectedType":"Double","containResource":false,"version":"1.0.1","compatibleState":0,"addableInputConfig":null,"addableOutputConfig":null,"portAddable":0},"hideInput":false,"valueList":[],"addManually":false},"targetPort":{"__referenceId":"0317be88-f3ba-68be-a5ae-81ad6ee88d73"},"isValid":true}],"owner":{"__referenceId":"15cef1bf-1690-7225-35e2-3a56d74c5924"},"hideInput":false,"relatedGroupPort":{"__referenceId":"d6b758d0-3d98-1871-d9a2-29e5a081de89"}},{"__referenceId":"8a645b24-a8b9-5bf9-8161-c987bdac753c"}],"outputPorts":[],"error":false,"groupEnable":false,"renamable":false,"nodeSettings":[{"key":"Description","property":[{"type":"String","section":"Description","key":"Node Desc","value":"","editable":false}]}],"relatedGroup":{"__referenceId":"69e987a9-727e-53f8-1aa4-8bf60e18b81a"},"placeholderType":"OUTPUT"},"hideInput":false,"relatedGroupPort":{"__class":"GroupPort","__uniqueId":"1459cb89-5324-588a-2824-731b3b482722","portName":"To Angle","type":"DATA","isInput":false,"isConnected":true,"isDynamic":true,"centerPosition":{"x":49418.02257881362,"y":50048.025809435516},"valueTypeName":"Double","portIndex":1,"portValue":null,"visible":true,"refEdges":[{"__class":"Edge","__uniqueId":"78dc1bfb-3060-734f-3729-5c478a089629","owner":{"__referenceId":"8cbbbf7b-0cd9-bce3-4889-e9ce71dc479f"},"type":"BEZIER","sourcePortPosition":{"x":49418.02257881362,"y":50048.025809435516},"targetPortPosition":{"x":49497.50022274535,"y":50047.21844408025},"sourcePort":{"__referenceId":"1459cb89-5324-588a-2824-731b3b482722"},"targetPort":{"__class":"ScriptPort","__uniqueId":"c2cb1b19-d734-5336-649d-82440e67e915","portName":"To","type":"DATA","isInput":true,"isConnected":true,"isDynamic":true,"centerPosition":{"x":49497.50022274535,"y":50047.21844408025},"valueTypeName":"Double","portIndex":5,"portValue":{"type":"Number","value":130},"visible":true,"refEdges":[{"__referenceId":"78dc1bfb-3060-734f-3729-5c478a089629"}],"owner":{"__referenceId":"c9d90f3a-e6ee-c64c-d970-002b7c909c0a"},"hideInput":false,"valueList":[],"addManually":false},"isValid":true}],"owner":{"__referenceId":"69e987a9-727e-53f8-1aa4-8bf60e18b81a"},"hideInput":false,"relatedPlaceholderPort":{"__referenceId":"8a645b24-a8b9-5bf9-8161-c987bdac753c"},"containsErrorEdgeInside":false}},"isValid":true}],"owner":{"__referenceId":"4a05810c-b71b-a28d-e05d-01d173e5a778"},"hideInput":false,"valueList":[],"addManually":false}],"error":false,"groupEnable":true,"renamable":false,"nodeSettings":[{"key":"Description","property":[{"type":"String","section":"Description","key":"Node Desc","value":"Calculate the sum of two inputs. You can click \"+\" to add more inputs. Supported types: Number, Vec2, Vec3, and Vec4.","editable":false}]}],"nodeName":"","templateGuid":"a06db1d5-3357-d608-25db-415522997904","curSelectedType":"Double","containResource":false,"version":"1.0.2","compatibleState":0,"addableInputConfig":{"isInput":true,"index":1,"baseName":"","initialStartIndex":"C","increaseStartIndex":"C","isFull":false},"addableOutputConfig":null,"portAddable":1},"hideInput":false,"valueList":[],"addManually":false},"isValid":true},{"__referenceId":"4938444a-d19b-0d77-eb1e-6e35c0548703"}],"owner":{"__referenceId":"74991fa6-e0c4-37be-6160-8c2c5a703392"},"hideInput":false,"valueList":[],"addManually":false}],"error":false,"groupEnable":true,"renamable":false,"nodeSettings":[{"key":"Description","property":[{"type":"String","section":"Description","key":"Node Desc","value":"Multiply two values. You can click \"+\" to add more inputs. Supported types: Number, Vec2, Vec3, and Vec4.","editable":false}]}],"nodeName":"","templateGuid":"f3d04790-2405-2f1e-f847-d8fb322377c6","curSelectedType":"Double","containResource":false,"version":"1.0.1","compatibleState":0,"addableInputConfig":{"isInput":true,"index":1,"baseName":"","initialStartIndex":"C","increaseStartIndex":"C","isFull":false},"addableOutputConfig":null,"portAddable":1},"hideInput":false,"valueList":[],"addManually":false},"isValid":true}],"owner":{"__referenceId":"3fe0f73a-5903-9d02-193c-6376e6a133db"},"hideInput":false,"relatedGroupPort":{"__class":"GroupPort","__uniqueId":"28507a4e-1450-79c3-69fa-6fc12c0ba14f","portName":"Total Angle Range","type":"DATA","isInput":true,"isConnected":false,"isDynamic":false,"centerPosition":{"x":49137.02257881362,"y":50048.025809435516},"valueTypeName":"Double","portIndex":1,"portValue":{"type":"Number","value":80},"visible":true,"refEdges":[],"owner":{"__referenceId":"69e987a9-727e-53f8-1aa4-8bf60e18b81a"},"hideInput":false,"relatedPlaceholderPort":{"__referenceId":"2e8033b0-a7af-068d-48e9-af90fbee711f"},"containsErrorEdgeInside":false}}],"error":false,"groupEnable":false,"renamable":false,"nodeSettings":[{"key":"Description","property":[{"type":"String","section":"Description","key":"Node Desc","value":"","editable":false}]}],"relatedGroup":{"__referenceId":"69e987a9-727e-53f8-1aa4-8bf60e18b81a"},"placeholderType":"INPUT"},{"__referenceId":"15cef1bf-1690-7225-35e2-3a56d74c5924"},{"__referenceId":"4a05810c-b71b-a28d-e05d-01d173e5a778"},{"__referenceId":"9a07b317-3676-84b9-3b9b-a6d4aa52aaba"},{"__referenceId":"74991fa6-e0c4-37be-6160-8c2c5a703392"}],"edgeList":[{"__referenceId":"e0c1e67a-c97b-3ff6-9d36-dec5c45004ca"},{"__referenceId":"603c4e97-badd-bbe0-d372-44038b0572f2"},{"__referenceId":"71033a66-1fcc-ba29-24f1-afb4e62c780d"},{"__referenceId":"bdeb997b-2bde-6e60-a479-ddb0c239df64"},{"__referenceId":"4938444a-d19b-0d77-eb1e-6e35c0548703"},{"__referenceId":"9c7e5917-a2ad-e495-d174-ce9589d67d31"},{"__referenceId":"fc89eebc-243f-1f3e-46d9-31c51bf14251"}],"owner":{"__class":"Container","__uniqueId":"e051c05c-6da8-75e7-b97e-1b61a7cd2467","graph":{"__referenceId":"8dff5d39-c77e-b4dd-12fd-95919262d695"},"parent":{"__referenceId":"49454a05-3ca9-7c85-a032-715a6bf7b5e6"},"root":{"__referenceId":"49454a05-3ca9-7c85-a032-715a6bf7b5e6"},"title":"Set Cannon Angles","subContainerManager":{"__class":"SubContainerManager","__uniqueId":"a909617a-1457-3e6a-100a-a85d258cb937","owner":{"__referenceId":"e051c05c-6da8-75e7-b97e-1b61a7cd2467"},"subContainers":[]},"containerType":1},"showMiniMap":false,"variableList":[{"__class":"GraphVariable","__uniqueId":"274b2fd2-3bc8-f4b3-54c0-26071b6adb10","isPublic":false,"variableType":"Number","variableName":"StartTurretAngle","isLocal":false,"initialValue":90,"owner":null}],"localVariableList":[],"showVariablePanel":false,"showSubGraphPanel":false},"type":"BEZIER","sourcePortPosition":{"x":48933.04139330203,"y":50052.196802974395},"targetPortPosition":{"x":49258.86856818156,"y":50023.459477034434},"sourcePort":{"__referenceId":"ee111d3c-beed-ccee-798c-4b422b7e4006"},"targetPort":{"__referenceId":"83296790-7466-c18d-b608-5b08a4ab3dc0"},"isValid":true},{"__referenceId":"fc89eebc-243f-1f3e-46d9-31c51bf14251"}],"owner":{"__referenceId":"3fe0f73a-5903-9d02-193c-6376e6a133db"},"hideInput":false,"relatedGroupPort":{"__referenceId":"c396e96c-31b9-5f3a-bbfe-e277de950b40"}},"containsErrorEdgeInside":false},{"__referenceId":"28507a4e-1450-79c3-69fa-6fc12c0ba14f"}],"outputPorts":[{"__referenceId":"d6b758d0-3d98-1871-d9a2-29e5a081de89"},{"__referenceId":"1459cb89-5324-588a-2824-731b3b482722"}],"error":false,"groupEnable":true,"renamable":false,"nodeSettings":[{"key":"Description","property":[{"type":"String","section":"Description","key":"Node Desc","value":"","editable":true}]}],"subContainer":{"__referenceId":"e051c05c-6da8-75e7-b97e-1b61a7cd2467"},"foldable":true,"expandable":true},"hideInput":false,"relatedPlaceholderPort":{"__referenceId":"0317be88-f3ba-68be-a5ae-81ad6ee88d73"},"containsErrorEdgeInside":false},"targetPort":{"__referenceId":"ffeced9d-ee7e-7027-2963-dcf5f81a277f"},"isValid":true}],"owner":{"__referenceId":"c9d90f3a-e6ee-c64c-d970-002b7c909c0a"},"hideInput":false,"valueList":[],"addManually":false},{"__referenceId":"c2cb1b19-d734-5336-649d-82440e67e915"},{"__class":"ScriptPort","__uniqueId":"6f2839be-3d5f-abb3-e8d8-a272e78c1938","portName":"Duration","type":"DATA","isInput":true,"isConnected":false,"isDynamic":false,"centerPosition":{"x":49497.50022274535,"y":50071.21844408026},"valueTypeName":"Double","portIndex":6,"portValue":{"type":"Number","value":2},"visible":true,"refEdges":[],"owner":{"__referenceId":"c9d90f3a-e6ee-c64c-d970-002b7c909c0a"},"hideInput":false,"valueList":[],"rangeValue":[{"minVal":0,"maxVal":1.7976931348623157e+308,"step":1}],"addManually":false},{"__class":"ScriptPort","__uniqueId":"8173593b-615c-999a-5d98-8657cbc37948","portName":"Interpolator","type":"DATA","isInput":true,"isConnected":false,"isDynamic":false,"centerPosition":{"x":49497.50022274535,"y":50095.21844408025},"valueTypeName":"String","portIndex":7,"portValue":{"type":"String","value":"Ease-in-out"},"visible":true,"refEdges":[],"owner":{"__referenceId":"c9d90f3a-e6ee-c64c-d970-002b7c909c0a"},"hideInput":false,"valueList":["Linear","Ease-in","Ease-out","Ease-in-out","Ease-out-in"],"addManually":false},{"__class":"ScriptPort","__uniqueId":"993e5796-463c-473e-b981-66779cda29f6","portName":"Loop","type":"DATA","isInput":true,"isConnected":false,"isDynamic":false,"centerPosition":{"x":49497.50022274535,"y":50119.21844408025},"valueTypeName":"Int","portIndex":8,"portValue":{"type":"Number","value":9999999},"visible":true,"refEdges":[],"owner":{"__referenceId":"c9d90f3a-e6ee-c64c-d970-002b7c909c0a"},"hideInput":false,"valueList":[],"rangeValue":[{"minVal":1,"maxVal":1.7976931348623157e+308,"step":1}],"addManually":false},{"__class":"ScriptPort","__uniqueId":"097c05b4-ba02-547f-f6be-097e140debad","portName":"Ping-pong","type":"DATA","isInput":true,"isConnected":false,"isDynamic":false,"centerPosition":{"x":49497.50022274535,"y":50143.21844408026},"valueTypeName":"Bool","portIndex":9,"portValue":{"type":"Bool","value":true},"visible":true,"refEdges":[],"owner":{"__referenceId":"c9d90f3a-e6ee-c64c-d970-002b7c909c0a"},"hideInput":false,"valueList":[],"addManually":false}],"outputPorts":[{"__class":"ScriptPort","__uniqueId":"d6840b59-548e-a2cb-f7cb-e6a989aa172e","portName":"Begin","type":"CONTROL","isInput":false,"isConnected":false,"isDynamic":false,"centerPosition":{"x":49751.50022274535,"y":49831.21844408025},"valueTypeName":"Pulse","portIndex":0,"portValue":null,"visible":true,"refEdges":[],"owner":{"__referenceId":"c9d90f3a-e6ee-c64c-d970-002b7c909c0a"},"hideInput":false,"valueList":[],"addManually":false},{"__class":"ScriptPort","__uniqueId":"7542d433-1854-da8c-12ab-886cc220e194","portName":"Stay","type":"CONTROL","isInput":false,"isConnected":false,"isDynamic":false,"centerPosition":{"x":49751.50022274535,"y":49855.21844408025},"valueTypeName":"Pulse","portIndex":1,"portValue":null,"visible":true,"refEdges":[],"owner":{"__referenceId":"c9d90f3a-e6ee-c64c-d970-002b7c909c0a"},"hideInput":false,"valueList":[],"addManually":false},{"__class":"ScriptPort","__uniqueId":"ace2a0d6-5c9c-f6f9-d15e-d5d42a6eb1b3","portName":"End","type":"CONTROL","isInput":false,"isConnected":false,"isDynamic":false,"centerPosition":{"x":49751.50022274535,"y":49879.21844408026},"valueTypeName":"Pulse","portIndex":2,"portValue":null,"visible":true,"refEdges":[],"owner":{"__referenceId":"c9d90f3a-e6ee-c64c-d970-002b7c909c0a"},"hideInput":false,"valueList":[],"addManually":false},{"__referenceId":"b83ec703-bb8d-a1cf-d5dc-bad6b705b696"}],"error":false,"groupEnable":true,"renamable":false,"nodeSettings":[{"key":"Description","property":[{"type":"String","section":"Description","key":"Node Desc","value":"Transition from one value to another according to a certain interpolator within a certain time range. Supported types: Number, Vec2, Vec3, Vec4, and Color.","editable":false}]}],"nodeName":"","templateGuid":"d8d6548e-e155-7781-8066-0575a4002a3d","curSelectedType":"Double","containResource":false,"version":"3.0.0","compatibleState":0,"addableInputConfig":null,"addableOutputConfig":null,"portAddable":0},"hideInput":false,"valueList":[],"addManually":false},"targetPort":{"__referenceId":"07be7a98-9c5b-d44a-74b0-f2b5be5bda56"},"isValid":true}],"owner":{"__referenceId":"19d15f19-b3c0-0605-2054-5533cf9c4dec"},"hideInput":false,"valueList":[],"addManually":false}],"outputPorts":[{"__class":"ScriptPort","__uniqueId":"a75c2735-7669-0146-5eee-64a4411ce16c","portName":"Trigger","type":"CONTROL","isInput":false,"isConnected":false,"isDynamic":false,"centerPosition":{"x":50009.294979698796,"y":49757.03325190168},"valueTypeName":"Pulse","portIndex":0,"portValue":null,"visible":true,"refEdges":[],"owner":{"__referenceId":"19d15f19-b3c0-0605-2054-5533cf9c4dec"},"hideInput":false,"valueList":[],"addManually":false}],"error":false,"groupEnable":true,"renamable":false,"nodeSettings":[{"key":"Description","property":[{"type":"String","section":"Description","key":"Node Desc","value":"","editable":false}]}],"nodeName":"","accessType":"SETTER","propertyInfo":{"__class":"PropertyInfo","__uniqueId":"1cac8734-77fe-3747-e715-af15baf78b8d","title":"Rotation","valueType":"Double","amgProperty":"rotation","amgObjectGuid":["Guid(16018021098500028857, 11086502365794207121)"],"uiAttributes":{"numberBox":true,"name":"°","range":{"min":0,"max":360},"pinToGraphAttr":{"pinObjectName":"IFTransform2d","pinPropertyName":"Rotation","pinObject":{"_class":39,"handle":4234138967},"pinProperty":"rotation"}},"scriptFileName":"Property","amgObjectType":["IFTransform2d"]},"pinError":false},{"__referenceId":"fc9032c3-0aaf-6c48-c4e2-6e1c118d77d0"},{"__referenceId":"c9d90f3a-e6ee-c64c-d970-002b7c909c0a"},{"__referenceId":"eeb05261-de97-b418-0e05-3ab7c4bf8d34"},{"__referenceId":"69e987a9-727e-53f8-1aa4-8bf60e18b81a"}],"edgeList":[{"__referenceId":"62b14b67-033c-28ec-28a5-f17c6aedafdd"},{"__referenceId":"65328099-c59d-39f7-bbd6-f1b68d9ddb28"},{"__referenceId":"4e1f74a3-b7b1-113f-82c7-3b4f87995567"},{"__referenceId":"a8d992db-eb42-f225-892e-d7facd301311"},{"__referenceId":"78dc1bfb-3060-734f-3729-5c478a089629"}],"owner":{"__referenceId":"49454a05-3ca9-7c85-a032-715a6bf7b5e6"},"showMiniMap":false,"variableList":[{"__referenceId":"274b2fd2-3bc8-f4b3-54c0-26071b6adb10"}],"localVariableList":[],"showVariablePanel":false,"showSubGraphPanel":false},"parent":null,"root":{"__referenceId":"49454a05-3ca9-7c85-a032-715a6bf7b5e6"},"title":"Main graph","subContainerManager":{"__class":"SubContainerManager","__uniqueId":"d52d921b-23a1-d203-6347-1eb021a2f6aa","owner":{"__referenceId":"49454a05-3ca9-7c85-a032-715a6bf7b5e6"},"subContainers":[{"key":"e051c05c-6da8-75e7-b97e-1b61a7cd2467","value":{"__referenceId":"e051c05c-6da8-75e7-b97e-1b61a7cd2467"}}]},"containerType":0}],"panelClosed":false,"panelCollapsed":false,"minimapOpen":false}